cdc_gateway/__init__.py
cdc_gateway/admin.py
cdc_gateway/app.py
cdc_gateway/flink_client.py
cdc_gateway/monitor.py
cdc_gateway/pipeline_manager.py
flink_cdc_gateway-1.0.7.dist-info/METADATA
flink_cdc_gateway-1.0.7.dist-info/WHEEL
flink_cdc_gateway-1.0.7.dist-info/entry_points.txt
flink_cdc_gateway-1.0.7.dist-info/top_level.txt
flink_cdc_gateway-1.0.7.dist-info/RECORD
