Metadata-Version: 2.4
Name: flink-cdc-gateway
Version: 1.0.7
Summary: Change Data Capture Gateway for Apache Flink
Home-page: https://github.com/mosiko1234/flink-cdc-gateway
Author: Moshe Eliya
Author-email: Moshe Eliya <mosiko1234@gmail.com>
License: Apache-2.0
Project-URL: Homepage, https://github.com/mosiko1234/flink-cdc-gateway
Project-URL: Bug Tracker, https://github.com/mosiko1234/flink-cdc-gateway/issues
Classifier: Development Status :: 4 - Beta
Classifier: Intended Audience :: Developers
Classifier: Intended Audience :: Information Technology
Classifier: Operating System :: OS Independent
Classifier: Programming Language :: Python :: 3
Classifier: Programming Language :: Python :: 3.8
Classifier: Programming Language :: Python :: 3.9
Classifier: Programming Language :: Python :: 3.10
Classifier: Topic :: Database
Classifier: Topic :: Software Development :: Libraries :: Python Modules
Requires-Python: >=3.8
Dynamic: author
Dynamic: home-page
Dynamic: requires-python
